[1,["87k4o1XytHMaKlQoQTP5uQ@f9941","02gCkbVH5DlKghJ8Ozz1UX@f9941","2bih6/Gb1LU55NFLrg6bK1@f9941","f2MP1jc6VCzqseGquOqppR@f9941","5cAWzrcNZH8bxf3wMeU1bw","85YLhbQA5Onqdx7InMBRPn","63Zv/ATi9MRK3Ru3VLCZBx@6c48a","9dxsRiaclLnoolbcVr5bb6@6c48a","0eVGD14cJLNpd5k18np64y@f9941","4dfenQoWlJGapofw/xbxDk@f9941","1cXkRgUntEA5DosReLqKlp@f9941","73H1nM7TxDao8nxkgk3Mss@f9941","05G1Sppt1B5q1/iIzTR1Dm@f9941","9dxsRiaclLnoolbcVr5bb6@f9941","63Zv/ATi9MRK3Ru3VLCZBx@f9941","3eDqLMPRpL0pCwMU+lnQaz@f9941","20jpZd2tBIs6rUhWwL3764","11LBQdCXtG9rvG+C5ORWXH"],["node","_spriteFrame","_textureSource","_defaultClip","root","payoutLabel","data"],[["cc.Node",["_name","_layer","_components","_prefab","_lpos","_parent","_children","_lrot","_euler","_lscale"],1,9,4,5,1,2,5,5,5],["cc.UITransform",["node","__prefab","_contentSize","_anchorPoint"],3,1,4,5,5],"cc.SpriteFrame",["cc.Animation",["playOnLoad","node","__prefab","_clips","_defaultClip"],2,1,4,3,6],["cc.Sprite",["_sizeMode","node","__prefab","_spriteFrame"],2,1,4,6],["cc.AudioClip",["_name","_native","_duration"],0],["cc.Prefab",["_name"],2],["cc.Node",["_name","_parent","_components","_prefab","_lpos"],2,1,12,4,5],["cc.CompPrefabInfo",["fileId"],2],["74e4c+bVqFMd6NI6BxmzccW",["node","__prefab","payoutLabel","audioClips"],3,1,4,1,3],["cc.PrefabInfo",["fileId","instance","targetOverrides","nestedPrefabInstanceRoots","root","asset"],-1,1,1],["cc.Label",["_string","_actualFontSize","_fontSize","_overflow","node","__prefab"],-1,1,4]],[[8,0,2],[10,0,1,2,3,4,5,5],[1,0,1,2,1],[4,1,2,3,1],[0,0,5,2,3,4,2],[0,0,1,5,2,3,4,3],[4,0,1,2,3,2],[1,0,1,2,3,1],[0,0,1,5,6,2,3,4,9,3],[5,0,1,2,4],[0,0,1,5,2,3,4,7,8,3],[0,0,5,2,3,4,9,2],[6,0,2],[0,0,6,2,3,4,2],[0,0,1,5,6,2,3,4,7,8,3],[0,0,1,5,6,2,3,4,3],[7,0,1,2,3,4,2],[1,0,1,1],[3,1,2,3,4,1],[3,0,1,2,3,4,2],[9,0,1,2,3,1],[11,0,1,2,3,4,5,5]],[[[[9,"chump-tower-vip",".mp3",3.96],-1],0,0,[],[],[]],[[[9,"chump-tower",".mp3",3.696],-1],0,0,[],[],[]],[[{"name":"chumpBanner","rect":{"x":3,"y":0,"width":760,"height":512},"offset":{"x":-1,"y":0},"originalSize":{"width":768,"height":512},"rotated":false,"capInsets":[0,0,0,0],"vertices":{"rawPosition":[-380,-256,0,380,-256,0,-380,256,0,380,256,0],"indexes":[0,1,2,2,1,3],"uv":[3,512,763,512,3,0,763,0],"nuv":[0.00390625,0,0.9934895833333334,0,0.00390625,1,0.9934895833333334,1],"minPos":{"x":-380,"y":-256,"z":0},"maxPos":{"x":380,"y":256,"z":0}},"packable":true,"pixelsToUnit":100,"pivot":{"x":0.5,"y":0.5},"meshType":0}],[2],0,[0],[2],[6]],[[{"name":"50x","rect":{"x":3,"y":0,"width":337,"height":173},"offset":{"x":-1,"y":1},"originalSize":{"width":345,"height":175},"rotated":false,"capInsets":[0,0,0,0],"vertices":{"rawPosition":[-168.5,-86.5,0,168.5,-86.5,0,-168.5,86.5,0,168.5,86.5,0],"indexes":[0,1,2,2,1,3],"uv":[3,175,340,175,3,2,340,2],"nuv":[0.008695652173913044,0.011428571428571429,0.9855072463768116,0.011428571428571429,0.008695652173913044,1,0.9855072463768116,1],"minPos":{"x":-168.5,"y":-86.5,"z":0},"maxPos":{"x":168.5,"y":86.5,"z":0}},"packable":true,"pixelsToUnit":100,"pivot":{"x":0.5,"y":0.5},"meshType":0}],[2],0,[0],[2],[7]],[[[12,"ChumpTowersWin"],[13,"ChumpTowersWin",[-6,-7,-8,-9,-10,-11,-12,-13,-14,-15,-16,-17,-18,-19],[[17,-2,[0,"9cgOmjo7FK/L3FbfLNnEdP"]],[18,-3,[0,"326MbokGBJOKJoKbfhn6ZP"],[23],24],[20,-5,[0,"9e6MkOYhZPL4S+/lmcSLtE"],-4,[25,26]]],[1,"c46/YsCPVOJYA4mWEpNYRx",null,null,null,-1,0],[1,0,114,0]],[14,"Stuntman",33554432,1,[-22,-23,-24,-25],[[2,-20,[0,"e3T4bJWJFHDZS1i991soz6"],[5,95,49]],[19,true,-21,[0,"fdiUZ44tlH4oz40C2iMIdp"],[14],15]],[1,"cd7CiNS/lIwYvQFO9Q/TqW",null,null,null,1,0],[1,-0.395,858.849,0],[3,0,0,0.7030534625478027,0.7111369972090789],[1,0,0,89.34499999999973]],[15,"torso",33554432,2,[-28,-29],[[2,-26,[0,"84SUrlf49FiJWAwMIwDsq3"],[5,49.6,54.439]],[6,0,-27,[0,"79AsEG8Z9OGIeapdekU0eX"],13]],[1,"8d13tgvfhBFa3vXk1zP9K7",null,null,null,1,0],[1,-20.745999999999867,13.546000000000163,0]],[8,"ChumpTower-002",33554432,1,[-32],[[2,-30,[0,"f7Eo7nwjpGkZXqufqBDCdB"],[5,613,944]],[3,-31,[0,"b1GP0g6ZlGDJZT0oxOue/E"],3]],[1,"92mWA2lfpGGq7eo0GnlsR/",null,null,null,1,0],[1,0,551.536,0],[1,0.5,0.5,1]],[8,"ChumpTower-001",33554432,1,[-35],[[2,-33,[0,"3cAE9Z3B9GpIChSpy1RmQa"],[5,613,944]],[3,-34,[0,"abdBVf+MpOV7T7MeGAUqTR"],5]],[1,"b39SurkCxAJJzaomHouJ4u",null,null,null,1,0],[1,0,157.833,0],[1,0.5,0.5,1]],[8,"ChumpTower",33554432,1,[-38],[[2,-36,[0,"cbXVsHm+FLz4039HfDiWIP"],[5,613,944]],[3,-37,[0,"752jDwHj9FJKvXv9Xk3kQC"],7]],[1,"25sOVu/LJM1JgDHSyC6vOn",null,null,null,1,0],[1,0,-233.336,0],[1,0.5,0.5,1]],[4,"Grass",1,[[2,-39,[0,"9657N7Q1pD0qrMTMFvfU0s"],[5,512,512]],[3,-40,[0,"2ekhGFQb1MbrnxVRYKmrlF"],0]],[1,"c3WTmrrzRFx7Ukd3/7VCfr",null,null,null,1,0],[1,0,-512.616,0]],[4,"Cloud2",1,[[2,-41,[0,"96pu3jlQJEob/dnRenJPNh"],[5,441,234]],[3,-42,[0,"0fDi2t3ltDGrOQx968rWwq"],1]],[1,"83xjhA5FxJA4hDDfdFzZJv",null,null,null,1,0],[1,279.90700000000004,742.972,0]],[5,"bathRoomCover-001",33554432,4,[[2,-43,[0,"6b1XUt62ZE9b1LUWsqI6GO"],[5,540,425]],[3,-44,[0,"54l0g0TCtOPrTdCyuCCrzX"],2]],[1,"65AoWJ+T9MuqGFQlDzBIYP",null,null,null,1,0],[1,-32.308,-162.662,0]],[5,"bathRoomCover-001",33554432,5,[[2,-45,[0,"cdi2Tp5/NBcpa2ykrCGRUr"],[5,540,425]],[3,-46,[0,"1etIG1GPdJVZ9xiLjiI0X4"],4]],[1,"e1AiT9gVBKXbMbs8ujoE0J",null,null,null,1,0],[1,-32.308,-162.662,0]],[5,"bathRoomCover-001",33554432,6,[[2,-47,[0,"599lFbZVBIvZGwoDdl90J/"],[5,540,425]],[3,-48,[0,"5auBemtmJCgJVfDbV1o3XJ"],6]],[1,"31j7+OGk1MUqSrrZPkBAon",null,null,null,1,0],[1,-32.308,257.866,0]],[10,"backArm",33554432,2,[[7,-49,[0,"48oZF7MbpK6bhKwvoVngQ2"],[5,26.982999999999997,18.406999999999996],[0,0.9745502694076995,0.536160187450406]],[6,0,-50,[0,"bddj9wBHVFNIycM5JeaJ/i"],8]],[1,"506ovd50JNO6vPtcXBEgjz",null,null,null,1,0],[1,-17.5215917993537,32.96514792776168,1.1890599270693278e-15],[3,0,0,-0.8392499429353243,0.543745835186859],[1,0,0,-114.122]],[5,"frontLeg",33554432,2,[[7,-51,[0,"75rm4KH7dAiI+cckSBUgxB"],[5,38.774,28],[0,0.9771136430543963,0.4000691744406668]],[6,0,-52,[0,"01sBWdXl1O0ZLGqLrbvNcZ"],9]],[1,"6eequQdRNObKI+5Aye6fuh",null,null,null,1,0],[1,-34.89999999999998,23.386000000000024,0]],[5,"backLeg",33554432,2,[[7,-53,[0,"d20Jx1mEhMZokjXol+oQUI"],[5,37.314,26.021],[0,0.9818641723296162,0.6275409944611969]],[6,0,-54,[0,"e6NxtnwupLzaoHbL0ZrAhy"],10]],[1,"9fqXuNpTdErJwv1rJ7N84z",null,null,null,1,0],[1,-35.57668249535709,2.6554909704262855,0]],[10,"frontArm",33554432,3,[[7,-55,[0,"1aTYPTOARAmKUJTzxutElE"],[5,40.579,18.19117842504405],[0,0.9550223344937652,0.6482931439203184]],[6,0,-56,[0,"8aFIN9aSJClLj9dLcUqAzx"],11]],[1,"c5YoBvd15KLopbr0HUx0KU",null,null,null,1,0],[1,-1.2490032007881382,-18.132739059216192,-3.413764162920034e-16],[3,0,0,0.8979315745521241,0.4401350786092188],[1,180,180,52.22499999999999]],[5,"head",33554432,3,[[7,-57,[0,"ef+pppsutPU48ve4RuVB19"],[5,80,71],[0,0.021874999999999978,0.5366760563380281]],[6,0,-58,[0,"d5npUHQgxEgKkOW2m4+esO"],12]],[1,"91Qw/F2MRKhqnKQiO9lwZl",null,null,null,1,0],[1,-1.9290000000003147,2.7809999999997217,0]],[11,"50x",1,[[2,-59,[0,"e14ZCh425HuJBtBxCL2Yab"],[5,337,173]],[3,-60,[0,"861czGOs1GrKJay5hWWC6W"],16]],[1,"6af11JrpREgppPMdC+n4x6",null,null,null,1,0],[1,-0.395,1094.827,0],[1,0.3,0.3,1]],[11,"chumpBanner",1,[[2,-61,[0,"c6/HN/lx5OObFUBFZUzHLC"],[5,760,512]],[3,-62,[0,"f3aqsliXZGRrMtViiclvfI"],17]],[1,"2dsvvZsgRAU63pEJ0bkM/N",null,null,null,1,0],[1,-0.395,1101.102,0],[1,0.5,0.5,1]],[16,"win",1,[[[2,-63,[0,"ee/SQEopxINqIP6lZUzWnG"],[5,280.82698254369967,50.39999999999999]],-64],4,1],[1,"0a8ZRVSTpBPJdIDEBMKaNM",null,null,null,1,0],[1,-0.395,955.101,0]],[4,"Cloud1",1,[[2,-65,[0,"351LGL2dtPHoab3l45jPAz"],[5,246,149]],[3,-66,[0,"c76SOqFZlPka3bHEst6o6L"],18]],[1,"566MlA+61FoaoPRaFQOOZH",null,null,null,1,0],[1,-324.286,929.901,0]],[4,"Grass-001",1,[[2,-67,[0,"92iXJz8RtJ+YpE6/udCDxV"],[5,512,512]],[3,-68,[0,"bfoX3KQ69AfIMmSH2+qHLi"],19]],[1,"cbnnraRqpNSJLShpa4Nu28",null,null,null,1,0],[1,509.799,-512.616,0]],[4,"Grass-002",1,[[2,-69,[0,"15RfEIEh9CNJfuzpNOo8I6"],[5,512,512]],[3,-70,[0,"24H6Rjeh9B66cHYGA0CmiD"],20]],[1,"08An7vjzJIarytwNBUEfn7",null,null,null,1,0],[1,999.883,-512.616,0]],[4,"Grass-003",1,[[2,-71,[0,"48ZgZL/p1IoqgTJgRHlXD1"],[5,512,512]],[3,-72,[0,"efLC4C//BKxpaX0xQFPJeS"],21]],[1,"acZ5bWb7hC07Jfm4WY0ZIf",null,null,null,1,0],[1,-509.799,-512.616,0]],[4,"Grass-004",1,[[2,-73,[0,"3fIFv0RMNOnZYVm7zO1XPf"],[5,512,512]],[3,-74,[0,"bbApJUQnxJPr3vJ96XbFZe"],22]],[1,"761tGZOmJHVazBgzQ8EX2C",null,null,null,1,0],[1,-1019.598,-512.616,0]],[21,"$220",51,50,2,19,[0,"dbGuu47S5CYL5jJgDtJxU0"]]],0,[0,4,1,0,0,1,0,0,1,0,5,25,0,0,1,0,-1,7,0,-2,8,0,-3,4,0,-4,5,0,-5,6,0,-6,2,0,-7,17,0,-8,18,0,-9,19,0,-10,20,0,-11,21,0,-12,22,0,-13,23,0,-14,24,0,0,2,0,0,2,0,-1,12,0,-2,13,0,-3,14,0,-4,3,0,0,3,0,0,3,0,-1,15,0,-2,16,0,0,4,0,0,4,0,-1,9,0,0,5,0,0,5,0,-1,10,0,0,6,0,0,6,0,-1,11,0,0,7,0,0,7,0,0,8,0,0,8,0,0,9,0,0,9,0,0,10,0,0,10,0,0,11,0,0,11,0,0,12,0,0,12,0,0,13,0,0,13,0,0,14,0,0,14,0,0,15,0,0,15,0,0,16,0,0,16,0,0,17,0,0,17,0,0,18,0,0,18,0,0,19,0,-2,25,0,0,20,0,0,20,0,0,21,0,0,21,0,0,22,0,0,22,0,0,23,0,0,23,0,0,24,0,0,24,0,6,1,74],[0,0,0,0,0,0,0,0,0,0,0,0,0,0,0,0,0,0,0,0,0,0,0,0,0,0,0],[1,1,1,1,1,1,1,1,1,1,1,1,1,1,-1,3,1,1,1,1,1,1,1,-1,3,-1,-2],[0,8,1,2,1,2,1,2,3,9,10,3,11,12,4,4,13,14,15,0,0,0,0,5,5,16,17]]]]
